[
  {
    "year": 1930,
    "stage": "DNQ"
  },
  {
    "year": 1934,
    "stage": "DNQ"
  },
  {
    "year": 1938,
    "stage": "DNQ"
  },
  {
    "year": 1950,
    "stage": "DNQ"
  },
  {
    "year": 1954,
    "stage": "DNQ"
  },
  {
    "year": 1958,
    "stage": "DNQ"
  },
  {
    "year": 1962,
    "stage": "DNQ"
  },
  {
    "year": 1966,
    "stage": "DNQ"
  },
  {
    "year": 1970,
    "stage": "DNQ"
  },
  {
    "year": 1974,
    "stage": "DNQ"
  },
  {
    "year": 1978,
    "stage": "DNQ"
  },
  {
    "year": 1982,
    "stage": "DNQ"
  },
  {
    "year": 1986,
    "stage": "DNQ"
  },
  {
    "year": 1990,
    "stage": "DNQ"
  },
  {
    "year": 1994,
    "stage": "DNQ"
  },
  {
    "year": 1998,
    "stage": "GS",
    "matches": [
      {
        "stage": "GS",
        "date": "1998-06-14",
        "opponent": "CRO",
        "opponent_full": "Croatia",
        "score": "1-3",
        "result": "L"
      },
      {
        "stage": "GS",
        "date": "1998-06-21",
        "opponent": "ARG",
        "opponent_full": "Argentina",
        "score": "0-5",
        "result": "L"
      },
      {
        "stage": "GS",
        "date": "1998-06-26",
        "opponent": "JPN",
        "opponent_full": "Japan",
        "score": "2-1",
        "result": "W"
      }
    ]
  },
  {
    "year": 2002,
    "stage": "DNQ"
  },
  {
    "year": 2006,
    "stage": "DNQ"
  },
  {
    "year": 2010,
    "stage": "DNQ"
  },
  {
    "year": 2014,
    "stage": "DNQ"
  },
  {
    "year": 2018,
    "stage": "DNQ"
  },
  {
    "year": 2022,
    "stage": "DNQ"
  },
  {
    "year": 2026,
    "stage": "DNQ",
    "matches": []
  }
]
